mongodb_connect/__init__.py
mongodb_connect/mongo_crud.py
MongoDBProject-0.1.0.dist-info/LICENSE
MongoDBProject-0.1.0.dist-info/METADATA
MongoDBProject-0.1.0.dist-info/WHEEL
MongoDBProject-0.1.0.dist-info/top_level.txt
MongoDBProject-0.1.0.dist-info/RECORD
